kozmoai_nasdaq/__init__.py
kozmoai_nasdaq/models/__init__.py
kozmoai_nasdaq/models/calendar_dividend.py
kozmoai_nasdaq/models/calendar_earnings.py
kozmoai_nasdaq/models/calendar_ipo.py
kozmoai_nasdaq/models/economic_calendar.py
kozmoai_nasdaq/models/equity_screener.py
kozmoai_nasdaq/models/equity_search.py
kozmoai_nasdaq/models/historical_dividends.py
kozmoai_nasdaq/models/top_retail.py
kozmoai_nasdaq/py.typed
kozmoai_nasdaq/utils/__init__.py
kozmoai_nasdaq/utils/helpers.py
kozmoai_nasdaq/utils/query_params.py
kozmoai_nasdaq-1.4.0.dev202506081902.dist-info/METADATA
kozmoai_nasdaq-1.4.0.dev202506081902.dist-info/WHEEL
kozmoai_nasdaq-1.4.0.dev202506081902.dist-info/entry_points.txt
kozmoai_nasdaq-1.4.0.dev202506081902.dist-info/RECORD
