Metadata-Version: 2.3
Name: kozmoai-nasdaq
Version: 1.4.0.dev202506081902
Summary: Nasdaq extension for KozmoAI
License: AGPL-3.0-only
Author: KozmoAI Team
Author-email: hello@kozmoai.co
Requires-Python: >=3.9,<4.0
Classifier: License :: OSI Approved :: GNU Affero General Public License v3
Classifier: Programming Language :: Python :: 3
Classifier: Programming Language :: Python :: 3.9
Classifier: Programming Language :: Python :: 3.10
Classifier: Programming Language :: Python :: 3.11
Classifier: Programming Language :: Python :: 3.12
Classifier: Programming Language :: Python :: 3.13
Requires-Dist: kozmoai-core (>=1.4.2,<2.0.0)
Requires-Dist: nasdaq-data-link (>=1.0.4,<2.0.0)
Requires-Dist: random-user-agent (>=1.0.1,<2.0.0)
